LICENSE.rst
MANIFEST.in
README.rst
pyproject.toml
setup.cfg
setup.py
galaxie_docs_theme/__init__.py
galaxie_docs_theme/defindex.html
galaxie_docs_theme/domainindex.html
galaxie_docs_theme/genindex-single.html
galaxie_docs_theme/genindex-split.html
galaxie_docs_theme/genindex.html
galaxie_docs_theme/globaltoc.html
galaxie_docs_theme/layout.html
galaxie_docs_theme/localtoc.html
galaxie_docs_theme/opensearch.xml
galaxie_docs_theme/page.html
galaxie_docs_theme/relations.html
galaxie_docs_theme/search.html
galaxie_docs_theme/searchbox.html
galaxie_docs_theme/sourcelink.html
galaxie_docs_theme/theme.conf
galaxie_docs_theme.egg-info/PKG-INFO
galaxie_docs_theme.egg-info/SOURCES.txt
galaxie_docs_theme.egg-info/dependency_links.txt
galaxie_docs_theme.egg-info/entry_points.txt
galaxie_docs_theme.egg-info/top_level.txt
galaxie_docs_theme/changes/frameset.html
galaxie_docs_theme/changes/rstsource.html
galaxie_docs_theme/changes/versionchanges.html
galaxie_docs_theme/static/basic.css_t
galaxie_docs_theme/static/doctools.js
galaxie_docs_theme/static/documentation_options.js_t
galaxie_docs_theme/static/file.png
galaxie_docs_theme/static/jquery-3.5.1.js
galaxie_docs_theme/static/jquery.js
galaxie_docs_theme/static/language_data.js_t
galaxie_docs_theme/static/minus.png
galaxie_docs_theme/static/plus.png
galaxie_docs_theme/static/searchtools.js
galaxie_docs_theme/static/underscore-1.13.1.js
galaxie_docs_theme/static/underscore.js