Metadata-Version: 2.1
Name: galaxie-docs-theme
Version: 2021.11
Summary: The Sphinx theme for the Galaxie docs and related projects
Home-page: https://gitlab.com/rtnp/galaxie-docs-theme/
Author: Tuxa
Author-email: tuxa@rtnp.org
License: GPLv3+
Download-URL: https://pypi.org/project/galaxie-docs-theme
Project-URL: Read the Docs, https://galaxie-docs-theme.readthedocs.io
Project-URL: GitLab, https://gitlab.com/rtnp/galaxie-docs-theme
Platform: UNKNOWN
Classifier: Intended Audience :: Developers
Classifier: Environment :: Console
Classifier: License :: OSI Approved :: GNU General Public License v3 or later (GPLv3+)
Classifier: Operating System :: OS Independent
Classifier: Topic :: Documentation
Classifier: Topic :: Software Development :: Documentation
Classifier: Programming Language :: Python
Classifier: Programming Language :: Python :: 3
License-File: LICENSE.rst
